meeseeksai/__init__.py
meeseeksai/meeseeksai.py
meeseeksai-0.1.6.dist-info/METADATA
meeseeksai-0.1.6.dist-info/WHEEL
meeseeksai-0.1.6.dist-info/entry_points.txt
meeseeksai-0.1.6.dist-info/RECORD
