Metadata-Version: 2.1
Name: meeseeksai
Version: 0.1.6
Summary: 
Author: Jaya
Author-email: jykur@vestas.com
Requires-Python: >=3.10,<4.0
Classifier: Programming Language :: Python :: 3
Classifier: Programming Language :: Python :: 3.10
Classifier: Programming Language :: Python :: 3.11
Requires-Dist: openai
Requires-Dist: python-dotenv (>=1.0.0,<2.0.0)
